README.md
setup.py
src/LTB_Symm.egg-info/PKG-INFO
src/LTB_Symm.egg-info/SOURCES.txt
src/LTB_Symm.egg-info/dependency_links.txt
src/LTB_Symm.egg-info/requires.txt
src/LTB_Symm.egg-info/top_level.txt
src/ltbsymm/__init__.py
src/ltbsymm/configuration.py
src/ltbsymm/misc.py
src/ltbsymm/symmetry.py
src/ltbsymm/tightbinding.py