Metadata-Version: 1.2
Name: LTB-Symm
Version: 1.0.0
Summary: Large Scale Tight Binding + Symmetries
Home-page: https://github.com/khsrali/LTB-Symm
Author: Ali Khosravi, Andrea Silva
Author-email: khsrali@gmail.com
License: GNU under General Public License v3.0
Keywords: tight-binding wave-function symmetries
Platform: UNKNOWN
Classifier: Development Status :: 4 - Beta
Classifier: Intended Audience :: Science/Research
Classifier: Topic :: Scientific/Engineering :: Physics
Classifier: License :: OSI Approved :: GNU General Public License v3 (GPLv3)
Classifier: Programming Language :: Python :: 3.7
Classifier: Programming Language :: Python :: 3.8
Requires-Python: >=3.7
